TOPSIS/__init__.py
TOPSIS/__main__.py
TOPSIS_Aadarsh_101803209-1.0.1.dist-info/Licence.txt
TOPSIS_Aadarsh_101803209-1.0.1.dist-info/METADATA
TOPSIS_Aadarsh_101803209-1.0.1.dist-info/WHEEL
TOPSIS_Aadarsh_101803209-1.0.1.dist-info/entry_points.txt
TOPSIS_Aadarsh_101803209-1.0.1.dist-info/top_level.txt
TOPSIS_Aadarsh_101803209-1.0.1.dist-info/RECORD
