Metadata-Version: 2.1
Name: TOPSIS-Aadarsh-101803209
Version: 1.0.1
Summary: TOPSIS
Home-page: UNKNOWN
Author: Aadarsh Gupta
Author-email: aadarshgupta875@gmail.com
License: MIT
Platform: UNKNOWN
Classifier: License :: OSI Approved :: MIT License
Classifier: Programming Language :: Python :: 3.6
Classifier: Programming Language :: Python :: 3.7
Classifier: Programming Language :: Python :: 3.8
